{
  "users": [
    {
      "id": 1,
      "name": "Adam Zemlak",
      "email": "a.zedlak@gmail.com",
      "phone": "(236) 354-2516"
    },
    {
      "id": 2,
      "name": "Martha Nikolaus",
      "email": "David.Collier67@yahoo.com",
      "phone": "(465) 604-8253"
    },
    {
      "id": 3,
      "name": "Micheal Ziemann",
      "email": "Amber.Luettgen@hotmail.com",
      "phone": "(268) 580-0537"
    },
    {
      "id": 4,
      "name": "Geraldine Hettinger",
      "email": "Fritz_Hermann61@gmail.com",
      "phone": "(554) 707-0618"
    },
    {
      "id": 5,
      "name": "Faye Feeney",
      "email": "Arlie47@hotmail.com",
      "phone": "(782) 925-2750"
    },
    {
      "id": 6,
      "name": "Shawna Blanda",
      "email": "Alexzander_Abernathy98@hotmail.com",
      "phone": "(908) 034-8625"
    },
    {
      "id": 7,
      "name": "Brandi Roob",
      "email": "Dariana.Predovic30@hotmail.com",
      "phone": "(360) 059-8896"
    },
    {
      "id": 8,
      "name": "Brandon Steuber",
      "email": "Anna_Mraz15@hotmail.com",
      "phone": "(379) 495-7255"
    },
    {
      "id": 9,
      "name": "Tabitha Mills",
      "email": "Ada.Legros15@yahoo.com",
      "phone": "(732) 274-1295"
    },
    {
      "id": 10,
      "name": "Dianne Dach Jr.",
      "email": "Janessa44@hotmail.com",
      "phone": "(511) 664-2886"
    },
    {
      "id": 11,
      "name": "Andy Miller",
      "email": "Stephania_Mueller@hotmail.com",
      "phone": "(501) 423-3509"
    },
    {
      "id": 12,
      "name": "Miss Jana Zulauf",
      "email": "Josh_Fay16@gmail.com",
      "phone": "(135) 709-0243"
    },
    {
      "id": 13,
      "name": "Miss Leslie Luettgen",
      "email": "Emory_Cruickshank37@hotmail.com",
      "phone": "(354) 351-1623"
    },
    {
      "id": 14,
      "name": "Louise Jenkins",
      "email": "Arianna92@gmail.com",
      "phone": "(789) 192-5962"
    },
    {
      "id": 15,
      "name": "Miss Randal Legros",
      "email": "Allene_Thiel60@gmail.com",
      "phone": "(015) 313-2609"
    },
    {
      "id": 16,
      "name": "Darla Kutch",
      "email": "Serenity_Kunze@yahoo.com",
      "phone": "(726) 336-8487"
    },
    {
      "id": 17,
      "name": "Miss Jo Greenfelder",
      "email": "Leonardo_Medhurst38@yahoo.com",
      "phone": "(820) 551-4289"
    },
    {
      "id": 18,
      "name": "Carol D'Amore",
      "email": "Marcelo.Schulist@gmail.com",
      "phone": "(734) 336-3843"
    },
    {
      "id": 19,
      "name": "Jeremy Fay",
      "email": "Joan3@yahoo.com",
      "phone": "(218) 782-5634"
    },
    {
      "id": 20,
      "name": "Edward Connelly",
      "email": "Fannie36@gmail.com",
      "phone": "(344) 194-1259"
    },
    {
      "id": 21,
      "name": "Minnie Wyman Jr.",
      "email": "Araceli23@yahoo.com",
      "phone": "(010) 218-7735"
    },
    {
      "id": 22,
      "name": "Emily Corwin",
      "email": "Horacio_Kautzer65@yahoo.com",
      "phone": "(068) 930-6882"
    },
    {
      "id": 23,
      "name": "Vickie Hansen",
      "email": "Shannon47@gmail.com",
      "phone": "(473) 698-8809"
    },
    {
      "id": 24,
      "name": "Preston Kuhn",
      "email": "Meagan.Stracke@yahoo.com",
      "phone": "(187) 037-1185"
    },
    {
      "id": 25,
      "name": "Van Feeney",
      "email": "Julianne.Volkman52@yahoo.com",
      "phone": "(221) 935-0765"
    },
    {
      "id": 26,
      "name": "Brendan Dibbert",
      "email": "Raoul.Quigley42@gmail.com",
      "phone": "(787) 477-7248"
    },
    {
      "id": 27,
      "name": "Katherine Fahey",
      "email": "Jennyfer.Moen@hotmail.com",
      "phone": "(206) 945-4394"
    },
    {
      "id": 28,
      "name": "Janet Denesik",
      "email": "Ubaldo_Johnston25@hotmail.com",
      "phone": "(662) 798-3764"
    },
    {
      "id": 29,
      "name": "Gloria Smith",
      "email": "Rosetta59@gmail.com",
      "phone": "(464) 879-0963"
    },
    {
      "id": 30,
      "name": "Rolando Gerhold PhD",
      "email": "Cleve.Aufderhar14@yahoo.com",
      "phone": "(778) 156-2942"
    },
    {
      "id": 31,
      "name": "Hector Gutkowski",
      "email": "Ericka_Conn13@hotmail.com",
      "phone": "(994) 408-6797"
    },
    {
      "id": 32,
      "name": "Raquel Bailey",
      "email": "Dorris_Kiehn63@hotmail.com",
      "phone": "(108) 864-3169"
    },
    {
      "id": 33,
      "name": "Danielle Schaden",
      "email": "Leda_Ward97@hotmail.com",
      "phone": "(288) 967-3412"
    },
    {
      "id": 34,
      "name": "Terrance Stamm",
      "email": "Alessandra_Green@gmail.com",
      "phone": "(486) 098-2328"
    },
    {
      "id": 35,
      "name": "Miss Tracey Maggio",
      "email": "Jameson.Hilll19@gmail.com",
      "phone": "(659) 416-9759"
    },
    {
      "id": 36,
      "name": "Van Beier",
      "email": "Trinity_West13@hotmail.com",
      "phone": "(099) 569-7060"
    },
    {
      "id": 37,
      "name": "Beulah Fritsch",
      "email": "Dudley_Boyer27@yahoo.com",
      "phone": "(971) 244-0405"
    },
    {
      "id": 38,
      "name": "Helen Lowe",
      "email": "Sarah_Trantow@gmail.com",
      "phone": "(027) 351-7952"
    },
    {
      "id": 39,
      "name": "Jamie Torphy",
      "email": "Carroll.Pfannerstill66@yahoo.com",
      "phone": "(268) 223-7117"
    },
    {
      "id": 40,
      "name": "Terrence Goyette",
      "email": "Tyson.Hodkiewicz2@gmail.com",
      "phone": "(345) 403-2037"
    },
    {
      "id": 41,
      "name": "Kent Cronin",
      "email": "Brayan_Reichel@gmail.com",
      "phone": "(072) 847-6805"
    },
    {
      "id": 42,
      "name": "Aubrey Swaniawski",
      "email": "Alvis4@yahoo.com",
      "phone": "(600) 678-7329"
    },
    {
      "id": 43,
      "name": "Dana Gibson",
      "email": "Barry87@yahoo.com",
      "phone": "(367) 873-1388"
    },
    {
      "id": 44,
      "name": "Melvin Gleichner",
      "email": "Iva_Russel@gmail.com",
      "phone": "(214) 301-2921"
    },
    {
      "id": 45,
      "name": "Leticia Dickens",
      "email": "Nat.Rice@hotmail.com",
      "phone": "(305) 012-7965"
    },
    {
      "id": 46,
      "name": "Allison Smitham",
      "email": "Conrad_Auer@hotmail.com",
      "phone": "(295) 742-4151"
    },
    {
      "id": 47,
      "name": "Peggy McLaughlin",
      "email": "Friedrich3@gmail.com",
      "phone": "(991) 392-9334"
    },
    {
      "id": 48,
      "name": "Hannah Kulas",
      "email": "Yasmeen_Trantow92@hotmail.com",
      "phone": "(203) 984-7585"
    },
    {
      "id": 49,
      "name": "Jody Rohan",
      "email": "Faustino3@yahoo.com",
      "phone": "(535) 299-2891"
    },
    {
      "id": 50,
      "name": "Ms. Jean Mraz",
      "email": "Paige51@gmail.com",
      "phone": "(448) 569-3697"
    },
    {
      "id": 51,
      "name": "Mitchell Hermiston",
      "email": "Vern.Greenholt@hotmail.com",
      "phone": "(972) 896-3104"
    },
    {
      "id": 52,
      "name": "Heidi Wuckert",
      "email": "Kenny.Dickinson17@gmail.com",
      "phone": "(954) 837-2426"
    },
    {
      "id": 53,
      "name": "Mrs. Cindy Harber",
      "email": "Anais_Veum@yahoo.com",
      "phone": "(522) 053-3030"
    },
    {
      "id": 54,
      "name": "Thelma Weber",
      "email": "Lukas54@hotmail.com",
      "phone": "(455) 838-8064"
    },
    {
      "id": 55,
      "name": "Antonio Hammes IV",
      "email": "Colin86@yahoo.com",
      "phone": "(183) 297-6037"
    },
    {
      "id": 56,
      "name": "Mrs. Candice Greenholt",
      "email": "Juston6@gmail.com",
      "phone": "(112) 793-7122"
    },
    {
      "id": 57,
      "name": "James Swaniawski",
      "email": "Daphne_Lemke40@gmail.com",
      "phone": "(160) 075-9225"
    },
    {
      "id": 58,
      "name": "Marguerite Hane",
      "email": "Earline85@gmail.com",
      "phone": "(635) 917-4959"
    },
    {
      "id": 59,
      "name": "Monique Daniel",
      "email": "Eve_Collier59@yahoo.com",
      "phone": "(951) 977-5963"
    },
    {
      "id": 60,
      "name": "Alonzo Sauer",
      "email": "Liza_McCullough98@gmail.com",
      "phone": "(137) 867-2735"
    },
    {
      "id": 61,
      "name": "Vera Schinner",
      "email": "Jettie.Boehm@gmail.com",
      "phone": "(380) 740-3532"
    },
    {
      "id": 62,
      "name": "Latoya Aufderhar",
      "email": "Modesta96@gmail.com",
      "phone": "(588) 916-8371"
    },
    {
      "id": 63,
      "name": "Samuel Green",
      "email": "Mathew33@yahoo.com",
      "phone": "(293) 797-2511"
    },
    {
      "id": 64,
      "name": "Anita Nienow",
      "email": "Vivianne_West@yahoo.com",
      "phone": "(809) 614-0212"
    },
    {
      "id": 65,
      "name": "Sophia Watsica",
      "email": "Francis66@hotmail.com",
      "phone": "(121) 984-1455"
    },
    {
      "id": 66,
      "name": "Mrs. Ida Kertzmann",
      "email": "Shawna.Gaylord@yahoo.com",
      "phone": "(076) 751-1572"
    },
    {
      "id": 67,
      "name": "Betsy Olson",
      "email": "Ward.Altenwerth@hotmail.com",
      "phone": "(150) 434-5088"
    },
    {
      "id": 68,
      "name": "Hugh Konopelski",
      "email": "Kelly.Ernser@gmail.com",
      "phone": "(404) 359-3973"
    },
    {
      "id": 69,
      "name": "Jacquelyn Fisher",
      "email": "Tyreek_Bruen@hotmail.com",
      "phone": "(416) 402-2548"
    },
    {
      "id": 70,
      "name": "Katrina MacGyver",
      "email": "Maximillian43@gmail.com",
      "phone": "(791) 023-2389"
    },
    {
      "id": 71,
      "name": "Luke Lakin DDS",
      "email": "Gardner_Crist48@gmail.com",
      "phone": "(028) 468-7325"
    },
    {
      "id": 72,
      "name": "Beth Blanda",
      "email": "Michael_Wiegand@yahoo.com",
      "phone": "(602) 181-9105"
    },
    {
      "id": 73,
      "name": "Cecil Buckridge",
      "email": "Burley_Cartwright@hotmail.com",
      "phone": "(510) 986-4999"
    },
    {
      "id": 74,
      "name": "Dana Carroll III",
      "email": "Eldred.Hintz95@hotmail.com",
      "phone": "(265) 190-7551"
    },
    {
      "id": 75,
      "name": "Ramona Hand",
      "email": "Malvina.Dach13@yahoo.com",
      "phone": "(330) 264-7550"
    },
    {
      "id": 76,
      "name": "Ethel Pfannerstill",
      "email": "Amara_Runte2@yahoo.com",
      "phone": "(639) 192-9469"
    },
    {
      "id": 77,
      "name": "Jessie Koelpin",
      "email": "Jayden.Bradtke@hotmail.com",
      "phone": "(039) 331-0321"
    },
    {
      "id": 78,
      "name": "Larry Daniel",
      "email": "Makenzie.Hayes@yahoo.com",
      "phone": "(306) 038-2543"
    },
    {
      "id": 79,
      "name": "Estelle Tromp",
      "email": "Rosetta.Stark@yahoo.com",
      "phone": "(000) 468-1341"
    },
    {
      "id": 80,
      "name": "Levi Skiles",
      "email": "Jacques_Maggio@hotmail.com",
      "phone": "(798) 145-9996"
    },
    {
      "id": 81,
      "name": "Dolores Hettinger",
      "email": "Garfield_Parisian@hotmail.com",
      "phone": "(599) 203-8635"
    },
    {
      "id": 82,
      "name": "Lynette Torphy III",
      "email": "Filomena_Morar73@gmail.com",
      "phone": "(368) 041-5419"
    },
    {
      "id": 83,
      "name": "Billy Ondricka",
      "email": "Gussie53@yahoo.com",
      "phone": "(775) 091-4877"
    },
    {
      "id": 84,
      "name": "Melinda Hudson",
      "email": "Monroe66@gmail.com",
      "phone": "(373) 473-3762"
    },
    {
      "id": 85,
      "name": "Lucia Runte",
      "email": "Theresa_Bednar37@yahoo.com",
      "phone": "(258) 970-6290"
    },
    {
      "id": 86,
      "name": "Cameron McKenzie",
      "email": "Ernest_Schmeler@yahoo.com",
      "phone": "(489) 544-0546"
    },
    {
      "id": 87,
      "name": "Patsy Marquardt",
      "email": "Shea_Lowe@yahoo.com",
      "phone": "(750) 545-7994"
    },
    {
      "id": 88,
      "name": "Stella Walsh",
      "email": "Gail_Connelly@hotmail.com",
      "phone": "(062) 159-1803"
    },
    {
      "id": 89,
      "name": "Josefina Rempel",
      "email": "Karolann_Casper@hotmail.com",
      "phone": "(015) 798-3461"
    },
    {
      "id": 90,
      "name": "Ms. Eric Spinka",
      "email": "Braden.Reinger@yahoo.com",
      "phone": "(865) 912-1616"
    },
    {
      "id": 91,
      "name": "Mr. Wendell Hahn",
      "email": "Alessandra76@hotmail.com",
      "phone": "(392) 858-8348"
    },
    {
      "id": 92,
      "name": "Gayle Morissette",
      "email": "Abelardo57@gmail.com",
      "phone": "(898) 717-0183"
    },
    {
      "id": 93,
      "name": "Carla Ledner",
      "email": "Janae78@yahoo.com",
      "phone": "(733) 357-7054"
    },
    {
      "id": 94,
      "name": "Natasha Grady",
      "email": "Eleazar.Purdy91@yahoo.com",
      "phone": "(497) 642-1420"
    },
    {
      "id": 95,
      "name": "Julius Ritchie",
      "email": "Esteban22@gmail.com",
      "phone": "(269) 412-5294"
    },
    {
      "id": 96,
      "name": "Ms. Johnny Will",
      "email": "Nikki.Leffler@yahoo.com",
      "phone": "(293) 132-9295"
    },
    {
      "id": 97,
      "name": "Kelli Kozey",
      "email": "Helmer32@gmail.com",
      "phone": "(729) 281-0380"
    },
    {
      "id": 98,
      "name": "Heather Hintz",
      "email": "Rossie_Toy77@yahoo.com",
      "phone": "(404) 802-4698"
    },
    {
      "id": 99,
      "name": "Lori Mueller",
      "email": "Roger.Keebler@gmail.com",
      "phone": "(182) 589-6367"
    },
    {
      "id": 100,
      "name": "Joe Gislason",
      "email": "j.gislason@gmail.com",
      "phone": "(671) 417-6334"
    }
  ]
}